ijroi/__init__.py
ijroi/ijroi.py
ijroi/version.py
ijroi/tests/__init__.py
ijroi/tests/test_ijroi.py
ijroi/tests/fixtures/float_point.roi
ijroi/tests/fixtures/freehand_circle.roi
ijroi/tests/fixtures/freehand_integer.roi
ijroi/tests/fixtures/generate_fixtures.js
ijroi/tests/fixtures/int_point.roi
ijroi/tests/fixtures/integer_rectangle.roi
ijroi/tests/fixtures/polygon_circle.roi
ijroi/tests/fixtures/polygon_integer.roi
ijroi/tests/fixtures/subpixel_rectangle.roi
ijroi/tests/fixtures/unit_rectangle.roi
ijroi-0.4.0.dist-info/DESCRIPTION.rst
ijroi-0.4.0.dist-info/METADATA
ijroi-0.4.0.dist-info/RECORD
ijroi-0.4.0.dist-info/WHEEL
ijroi-0.4.0.dist-info/metadata.json
ijroi-0.4.0.dist-info/pbr.json
ijroi-0.4.0.dist-info/top_level.txt
