Metadata-Version: 2.0
Name: ijroi
Version: 0.4.0
Summary: Reads ImageJ ROIs.
Home-page: https://github.com/tdsmith/ijroi
Author: Tim D. Smith
Author-email: ijroi@tim-smith.us
License: MIT
Platform: any
Classifier: Development Status :: 4 - Beta
Classifier: Intended Audience :: Science/Research
Classifier: Topic :: Scientific/Engineering
Classifier: License :: OSI Approved :: MIT License
Classifier: Programming Language :: Python :: 2.7
Classifier: Programming Language :: Python :: 3.6
Requires-Dist: numpy
